aiobus/__init__.py
aiobus/aiocontext.py
aiobus/base.py
aiobus/errors.py
aiobus/redis.py
aiobus/ring.py
aiobus-1.0.6.dist-info/LICENSE
aiobus-1.0.6.dist-info/METADATA
aiobus-1.0.6.dist-info/WHEEL
aiobus-1.0.6.dist-info/top_level.txt
aiobus-1.0.6.dist-info/RECORD
