Metadata-Version: 2.1
Name: aiobus
Version: 1.0.6
Summary: An event-bus application layer, supports redis
Home-page: https://github.com/Sirius-social/aiobus
Author: Networks Synergy
Author-email: support@socialsirius.com
Maintainer: Pavel Minenkov <minikspb@gmail.com>
License: Apache License
Keywords: aioredis,aiobus,redis,distributed,asyncio,bus
Platform: UNKNOWN
Classifier: License :: OSI Approved :: Apache Software License
Classifier: Intended Audience :: Developers
Classifier: Programming Language :: Python :: 3
Classifier: Programming Language :: Python :: 3.7
Classifier: Programming Language :: Python :: 3.8
Classifier: Operating System :: POSIX
Classifier: Operating System :: MacOS :: MacOS X
Classifier: Operating System :: Microsoft :: Windows
Requires-Python: >=3.5
License-File: LICENSE
Requires-Dist: aioredis (>=1.3.1)
